setup.py
brokenegg/__init__.py
brokenegg/broken.py
brokenegg.egg-info/PKG-INFO
brokenegg.egg-info/SOURCES.txt
brokenegg.egg-info/dependency_links.txt
brokenegg.egg-info/not-zip-safe
brokenegg.egg-info/top_level.txt