Metadata-Version: 1.0
Name: brokenegg
Version: 0.0.0
Summary: Ann egg with SyntaxErrors
Home-page: UNKNOWN
Author: John Carr
Author-email: john.carr@isotoma.com
License: Apache Software License
Platform: UNKNOWN
